MANIFEST.in
README.txt
setup.py
o2w/__init__.py
o2w/core/__init__.py
o2w/core/admin.py
o2w/core/mail.py
o2w/core/models.py
o2w/core/utils.py
o2w_core.egg-info/PKG-INFO
o2w_core.egg-info/SOURCES.txt
o2w_core.egg-info/dependency_links.txt
o2w_core.egg-info/top_level.txt